blobxfer/__init__.py
blobxfer/api.py
blobxfer/retry.py
blobxfer/util.py
blobxfer/version.py
blobxfer/models/__init__.py
blobxfer/models/azure.py
blobxfer/models/crypto.py
blobxfer/models/download.py
blobxfer/models/metadata.py
blobxfer/models/offload.py
blobxfer/models/options.py
blobxfer/models/resume.py
blobxfer/models/synccopy.py
blobxfer/models/upload.py
blobxfer/operations/__init__.py
blobxfer/operations/crypto.py
blobxfer/operations/download.py
blobxfer/operations/md5.py
blobxfer/operations/progress.py
blobxfer/operations/resume.py
blobxfer/operations/synccopy.py
blobxfer/operations/upload.py
blobxfer/operations/azure/__init__.py
blobxfer/operations/azure/file.py
blobxfer/operations/azure/blob/__init__.py
blobxfer/operations/azure/blob/append.py
blobxfer/operations/azure/blob/block.py
blobxfer/operations/azure/blob/page.py
blobxfer_cli/__init__.py
blobxfer_cli/cli.py
blobxfer_cli/settings.py
blobxfer-1.11.0.dist-info/LICENSE
blobxfer-1.11.0.dist-info/METADATA
blobxfer-1.11.0.dist-info/WHEEL
blobxfer-1.11.0.dist-info/entry_points.txt
blobxfer-1.11.0.dist-info/top_level.txt
blobxfer-1.11.0.dist-info/RECORD
