Metadata-Version: 2.1
Name: blobxfer
Version: 1.11.0
Summary: Azure storage transfer tool and data movement library
Home-page: https://github.com/Azure/blobxfer
Author: Microsoft Corporation
Author-email: 
License: MIT
Keywords: azure,storage,blob,files,transfer,copy,smb,cifs,blobxfer,azcopy
Platform: any
Classifier: Development Status :: 5 - Production/Stable
Classifier: Environment :: Console
Classifier: Intended Audience :: Developers
Classifier: Intended Audience :: End Users/Desktop
Classifier: Intended Audience :: Information Technology
Classifier: Intended Audience :: System Administrators
Classifier: License :: OSI Approved :: MIT License
Classifier: Operating System :: OS Independent
Classifier: Programming Language :: Python :: 3
Classifier: Topic :: Software Development :: Libraries :: Python Modules
Classifier: Topic :: Utilities
License-File: LICENSE
Requires-Dist: azure-storage-blob (<3,>=2.1.0)
Requires-Dist: azure-storage-file (<3,>=2.1.0)
Requires-Dist: bitstring (<4,>=3.1.9)
Requires-Dist: click (<9,>=8.0.1)
Requires-Dist: cryptography (>=3.3.2)
Requires-Dist: python-dateutil (<3,>=2.8.2)
Requires-Dist: requests (<3,>=2.26.0)
Requires-Dist: ruamel.yaml (>=0.17.3)
